pkglog/__init__.py
pkglog/__main__.py
pkglog/pkglog.py
pkglog/parsers/apt.py
pkglog/parsers/dnf.py
pkglog/parsers/pacman.py
pkglog/parsers/xbps.py
pkglog/parsers/zypper.py
pkglog-1.34.dist-info/METADATA
pkglog-1.34.dist-info/WHEEL
pkglog-1.34.dist-info/entry_points.txt
pkglog-1.34.dist-info/top_level.txt
pkglog-1.34.dist-info/RECORD
