Metadata-Version: 2.4
Name: pkglog
Version: 1.34
Summary: Reports concise log of package changes
Author-email: Mark Blakeney <mark.blakeney@bullet-systems.net>
License-Expression: GPL-3.0-or-later
Project-URL: Homepage, https://github.com/bulletmark/pkglog
Keywords: pacman,apt-get,apt,dnf
Classifier: Programming Language :: Python :: 3
Requires-Python: >=3.10
Requires-Dist: argparse-from-file
